MANIFEST.in
setup.cfg
setup.py
version.py
src/cgcloud/__init__.py
src/cgcloud/spark_tools/__init__.py
src/cgcloud_spark_tools.egg-info/PKG-INFO
src/cgcloud_spark_tools.egg-info/SOURCES.txt
src/cgcloud_spark_tools.egg-info/dependency_links.txt
src/cgcloud_spark_tools.egg-info/namespace_packages.txt
src/cgcloud_spark_tools.egg-info/requires.txt
src/cgcloud_spark_tools.egg-info/top_level.txt