Metadata-Version: 1.0
Name: cgcloud-spark-tools
Version: 1.3.3a1.dev216
Summary: Setup and manage a Apache Spark cluster in EC2
Home-page: https://github.com/BD2KGenomics/cgcloud
Author: Hannes Schmidt
Author-email: hannes@ucsc.edu
License: UNKNOWN
Platform: UNKNOWN
